{
  "sections": [
    {
      "title": "一、摘要",
      "content": [
        {
          "type": "text",
          "text": "英特爾（Intel Corporation, INTC）為全球半導體產業的領導者，長年主宰x86處理器市場。近年公司於先進製程技術上落後主要競爭對手，導致本業獲利能力明顯下滑、經營壓力加劇。目前財務結構因積極資本支出導致固定資產與負債提升，財務風險呈上升趨勢。儘管如此，現階段公司股價根據營收比屬於偏低、低估區間，吸引著價值投資人的關注。近期技術面自超賣區反彈，多頭排列逐步形成，但長線格局仍有壓力。展望未來，公司須持續推動製程與AI轉型、管理現金流及營運效率，同時須應對產業競爭、國際環境與技術進步挑戰。整體而言，本報告對英特爾維持「審慎偏多」看法，但認為投資人宜密切關注公司改革進度與產業發展趨勢。"
        }
      ]
    },
    {
      "title": "二、公司簡介",
      "content": [
        {
          "type": "text",
          "text": "英特爾公司成立於1968年，總部位於美國加州，是全球知名的半導體設計與製造巨擘。公司以IDM（垂直整合製造）的模式橫跨IC設計、製造、封裝領域，主力產品涵蓋各級x86架構處理器（如Core、Xeon、Pentium）、晶片組、記憶體、嵌入式系統以及物聯網解決方案等，深度應用於個人電腦、伺服器、企業資料中心、車用電子、AI、5G和自駕車等多元領域。現階段，公司積極布局AI、5G、資料中心、製造服務（IFS）、FPGA等新興應用，同時強化先進製程與國際產能擴展。現任CEO為業界資深領導Lip Boutin，他自2024年上任即推動組織改革、技術創新及管理重組，以應對全球半導體產業大環境的劇烈變化與競爭升級。"
        }
      ]
    },
    {
      "title": "三、財務重點",
      "content": [
        {
          "type": "points",
          "points": [
            {
              "title": "1.獲利能力：",
              "description": "近兩年毛利率大致維持於35%~45%，但營業利益率及淨利率大幅波動，部分季度出現負值，反映公司本業壓力大，近兩季雖回正但僅約2~3%，獲利動能疲弱。"
            },
            {
              "title": "2.成長性：",
              "description": "近季營收成長率大幅波動，2024年部分季度出現負成長，稅前與稅後淨利深陷衰退，營運壓力明顯。"
            },
            {
              "title": "3.財務結構：",
              "description": "固定資產比持續攀升至57.1%，股東權益比略為下修，負債比率從44%提升至49%，長期舉債壓力增加，資本穩定性仍可但風險升溫。"
            },
            {
              "title": "4.營運效率：",
              "description": "應收帳款與存貨週轉略為改善，固定與總資產週轉率偏低，資產利用尚待升級。"
            },
            {
              "title": "5.現金流量與財務風險：",
              "description": "經營現金流波動大，有季度為負，財務風險指標下滑，利息保障倍數僅約1倍，顯示償債壓力提升，整體須密切關注現金流與負債管理。"
            }
          ]
        }
      ]
    },
    {
      "title": "四、產業分析",
      "content": [
        {
          "type": "text",
          "text": "全球半導體產業正處於高波動與快速進階的發展階段。AI、大數據、5G、自駕車等新興應用強勢帶動需求，各國紛紛推動本土半導體政策，並加速研發先進製程與高效能運算技術。英特爾在資料中心、PC處理器等核心領域仍具市場主導地位，但製程技術進展落後，使其面臨台積電、三星、AMD、NVIDIA等公司的強大競爭壓力。IDM垂直整合模式讓英特爾具備差異化，但需求波動與地緣政治風險無可避免。未來AI、雲端、車用半導體持續成長，美國政府相關補貼亦為公司中長期利多，惟須持續突破技術瓶頸與提升經營效率，才能在激烈競爭中保有成長動能。"
        }
      ]
    },
    {
      "title": "五、價值評估",
      "content": [
        {
          "type": "text",
          "text": "以2025年6月20日收盤價21.08美元觀察，目前位於營收比估值分位的「便宜點」（17.63美元）至「偏低點」（23.97美元）區間，低於同業與過往歷史合理價格（30.31美元），呈現明顯低估，具備價值投資吸引力。雖缺乏本益比與現金流分位等其他詳細數據，但僅從營收比而言，若公司未來營運企穩，有望反映安全邊際。不過，目前公司本業獲利尚未轉強，需綜合考慮基本面改善步調再行決策。"
        }
      ]
    },
    {
      "title": "六、技術分析",
      "content": [
        {
          "type": "text",
          "text": "近期技術面呈現跌深反彈：5月底KD進入超賣區後強力反彈，高檔修正後現處中性水平；MACD指標從長期空方慢慢轉為多方控盤，差離數值正向擴大，顯多頭動能逐漸增強。均線方面，中短期均線已多頭排列，年線下滑暗示長線整理尚未結束。整體技術結構顯示股價築底反彈，短線可偏多看待，但需提防短期回測與盤整風險，建議盤中留意20.8~20.9美元區間支撐。"
        }
      ]
    },
    {
      "title": "七、重點新聞",
      "content": [
        {
          "type": "points",
          "points": [
            {
              "title": "1.營運與財報壓力：",
              "description": "因蘋果合作終止、競爭加劇，成本與毛利承壓，Q1財報雖優預期但營收未明顯回升；Q2展望保守致影響股價。"
            },
            {
              "title": "2.CEO更替與改革契機：",
              "description": "新任CEO具改革決心，推動組織重組與裁員，冀強化製造、AI及非核心業務剝離，市場預期改革效應。"
            },
            {
              "title": "3.產業競爭與動能：",
              "description": "數據中心、AI與鑄造服務為潛在成長點，但鑄造業務預期至2026年前仍虧損，需觀察改革與轉型進程。"
            },
            {
              "title": "4.國際及政策變數：",
              "description": "美國半導體自製政策利多，但中美貿易與出口管制令公司成本與全球方案複雜化。"
            },
            {
              "title": "5.競爭環境嚴峻：",
              "description": "AWS自製芯片、AMD、NVIDIA、台積電等競爭者進一步壓縮Intel高端市占，市場疑慮依舊。"
            },
            {
              "title": "6.庫存與市場展望：",
              "description": "部分PC需求受提前拉貨拉抬，產業長期需求、技術升級與雲端市場發展仍需持續追蹤。"
            },
            {
              "title": "7.政府補貼與資金：",
              "description": "公司高度依賴美國政府補貼以布局本土先進製造，若資金募集困難將影響轉型步調。"
            }
          ]
        }
      ]
    },
    {
      "title": "八、買賣建議",
      "content": [
        {
          "type": "text",
          "text": "基於以上深入分析，英特爾現階段基本面雖存在挑戰，但目前估值屬於偏低區間，技術面也顯現築底反彈的跡象；然而由於財務結構仍有惡化風險、盈利能力短期難言樂觀，加上產業競爭壓力強勁，建議以「審慎偏多／區間低接」操作為主：\n- 投資人可考慮於21美元以下分批布局，偏價值投資或逢低承接；\n- 若短期積極型投資人，建議設好停損於20.5美元以下，後續突破22~23美元可伺機加碼；\n- 長線投資人則須密切關注公司製程技術改革、AI與雲端業務進度，以及現金流與資本支出管理。\n\n若未來公司能有效改善本業獲利、現金流及資產利用效率，則股價回升空間可期；反之若改革不及預期，則需審慎評估風險並適時停利或撤出。"
        }
      ]
    },
    {
      "title": "九、結論",
      "content": [
        {
          "type": "text",
          "text": "英特爾作為全球半導體龍頭之一，具備產業地位與品牌基礎，但近年因製程落後與競爭加劇，導致獲利能力衰退、財務壓力上升。現階段股價處於低估區呈現投資吸引力，技術面亦逐步修復，但長遠成長性將取決於領導團隊改革成效、技術升級、AI與製造轉型進展，以及國際產業政策變動。後續可持續觀察財報數據、關鍵新技術量產進度、政府補貼政策、產業景氣循環及國際貿易動態，適時調整持股策略，以謀求最佳報酬風險比。"
        }
      ]
    }
  ]
}